Metadata-Version: 2.1
Name: calibdiff
Version: 0.1.0
Summary: A PyTorch-based differential camera calibration library for intrinsic, extrinsic, and stereo camera calibration.
Home-page: https://github.com/DIYer22/calibdiff
Author: DIYer22
Author-email: ylxx@live.com
License: UNKNOWN
Platform: UNKNOWN
Classifier: Topic :: Software Development :: Libraries :: Python Modules
Classifier: Programming Language :: Python :: 3
Classifier: License :: OSI Approved :: MIT License
Classifier: Operating System :: OS Independent
